Workbook

Sheet PORTADA
B2: LABORATORIO DE INTEGRACIÓN DE SISTEMAS CONTABILIDAD ANALÍTICA PLANIFICACIÓN Y PRESUPUESTO DE PROYECTOS TI
B8: Proyecto: Desarrollo de Sistema de Información para Gestión Logística en Empresa de Distribución de Productos Electrónicos
B10: Presentado por: | C10: Alejandro De Mendoza
B11: Materia: | C11: Integración de Sistemas
B12: Actividad: | C12: Laboratorio – Contabilidad Analítica y Planificación de Proyectos
B13: Duración: | C13: 8 meses
B14: País / Ciudad: | C14: Colombia – Bogotá D.C.
B15: Moneda: | C15: Pesos Colombianos (COP)
B16: Fecha de elaboración: | C16: Mayo 2026
B17: Versión: | C17: 1.0
B19: CONTENIDO DEL LIBRO
B20: PORTADA | C20: Carátula e índice del laboratorio
B21: SUPUESTOS | C21: Parámetros y variables del proyecto
B22: REC_HUMANO | C22: Equipo de trabajo, salarios y prestaciones
B23: ACTIVIDADES | C23: Actividades por recurso humano (tabla principal)
B24: REC_TECNICO | C24: Hardware, software y licencias
B25: IMPUESTOS | C25: IVA y cargas tributarias en Colombia
B26: COSTOS_OPERATIVOS | C26: Servicios públicos y otros costos operativos
B27: IMPREVISTOS | C27: Fondo de contingencias (10%)
B28: RESUMEN_COSTOS | C28: Consolidado total de costos del proyecto
B29: RENTABILIDAD | C29: Análisis de rentabilidad e indicadores financieros
B30: CLASIFICACION | C30: Clasificación analítica de costos
B31: GANTT | C31: Cronograma de actividades – Diagrama de Gantt
B32: RESUMEN_EJECUTIVO | C32: Dashboard ejecutivo del proyecto

Sheet SUPUESTOS
B1: SUPUESTOS Y PARÁMETROS DEL PROYECTO
B2: Proyecto: Sistema de Información – Gestión Logística (Distribución Electrónicos)
B4: 1. PARÁMETROS GENERALES
B5: Duración del proyecto (meses) | C5: 8 | D5: [meses] Fijado por el cliente
B6: Horas laborables por semana | C6: 40 | D6: [horas] Jornada legal Colombia
B7: Semanas por mes | C7: 4.33 | D7: [sem/mes] Promedio
B8: Horas laborables por mes | C8: 173 | D8: [horas] =40×4.33
B9: Margen de ganancia | C9: 0.3 | D9: [%] 30% sobre costo total
B10: Fondo de imprevistos | C10: 0.1 | D10: [%] 10% sobre costo total
B11: IVA compras tecnológicas (Colombia) | C11: 0.19 | D11: [%] Estatuto Tributario
B12: Carga prestacional (aprox.) | C12: 0.52 | D12: [%] Suma prestaciones Col.
B14: 2. DETALLE CARGA PRESTACIONAL COLOMBIA
B15: Concepto | C15: Porcentaje | D15: Notas
B16: Salud (aporte empleador) | C16: 0.085 | D16: Ley 100 de 1993
B17: Pensión (aporte empleador) | C17: 0.12 | D17: Ley 100 de 1993
B18: ARL promedio | C18: 0.00522 | D18: Decreto 1772 de 1994
B19: Caja de Compensación | C19: 0.04 | D19: Ley 21 de 1982
B20: Cesantías | C20: 0.0833 | D20: CST Art. 249
B21: Intereses sobre cesantías | C21: 0.01 | D21: Ley 52 de 1975
B22: Prima de servicios | C22: 0.0833 | D22: CST Art. 306
B23: Vacaciones | C23: 0.0417 | D23: CST Art. 186
B24: SENA | C24: 0.02 | D24: Ley 119 de 1994
B25: ICBF | C25: 0.03 | D25: Decreto 118 de 1957
B26: TOTAL CARGA PRESTACIONAL | C26: =SUM(C16:C25) -> 0.51852

Sheet REC_HUMANO
B1: RECURSO HUMANO – SALARIOS Y PRESTACIONES SOCIALES
B2: Proyecto: Sistema de Información – Gestión Logística
B4: Cargo / Perfil | C4: Cantidad | D4: Salario Mensual (COP) | E4: Meses en Proyecto | F4: Subtotal Salario Base (COP) | G4: Prestaciones 52% (COP)
B5: Director de Proyecto | C5: 1 | D5: 8000000 | E5: 8 | F5: =C5*D5*E5 -> 64000000 | G5: =F5*SUPUESTOS!C12 -> 33280000
B6: Analista de Requerimientos | C6: 1 | D6: 5500000 | E6: 2 | F6: =C6*D6*E6 -> 11000000 | G6: =F6*SUPUESTOS!C12 -> 5720000
B7: Arquitecto de Software | C7: 1 | D7: 7000000 | E7: 3 | F7: =C7*D7*E7 -> 21000000 | G7: =F7*SUPUESTOS!C12 -> 10920000
B8: Desarrollador Backend Senior | C8: 2 | D8: 5500000 | E8: 5 | F8: =C8*D8*E8 -> 55000000 | G8: =F8*SUPUESTOS!C12 -> 28600000
B9: Desarrollador Frontend | C9: 1 | D9: 5000000 | E9: 5 | F9: =C9*D9*E9 -> 25000000 | G9: =F9*SUPUESTOS!C12 -> 13000000
B10: Diseñador UX/UI | C10: 1 | D10: 4500000 | E10: 2 | F10: =C10*D10*E10 -> 9000000 | G10: =F10*SUPUESTOS!C12 -> 4680000
B11: Ingeniero QA / Pruebas | C11: 1 | D11: 4500000 | E11: 2 | F11: =C11*D11*E11 -> 9000000 | G11: =F11*SUPUESTOS!C12 -> 4680000
B12: Administrador de Base de Datos | C12: 1 | D12: 5000000 | E12: 2 | F12: =C12*D12*E12 -> 10000000 | G12: =F12*SUPUESTOS!C12 -> 5200000
B13: Especialista en Integración TI | C13: 1 | D13: 6000000 | E13: 3 | F13: =C13*D13*E13 -> 18000000 | G13: =F13*SUPUESTOS!C12 -> 9360000
B14: Soporte e Implementación | C14: 1 | D14: 3500000 | E14: 2 | F14: =C14*D14*E14 -> 7000000 | G14: =F14*SUPUESTOS!C12 -> 3640000
B15: TOTAL SALARIOS BASE | F15: =SUM(F5:F14) -> 229000000 | G15: =SUM(G5:G14) -> 119080000
B16: TOTAL MANO DE OBRA (Salarios + Prestaciones) | F16: =F15+G15 -> 348080000

Sheet ACTIVIDADES
B1: ACTIVIDADES POR RECURSO HUMANO – CONTABILIDAD ANALÍTICA
B2: Proyecto: Sistema de Información – Gestión Logística (8 meses / 173 hrs/mes)
B4: No | C4: Actividad / Tarea | D4: Recurso Humano | E4: Tiempo (horas) | F4: Coste RH x Hora (COP) | G4: Sub Total Recurso Humano | H4: Tiempo (horas) Recurso Técnico | I4: Coste RT x Hora (COP) | J4: Sub Total Recurso Técnico
B5: ACT001 | C5: Levantamiento y análisis de requerimientos | D5: Analista de Requerimientos | E5: 336 | F5: 31791.91 | G5: =E5*F5 -> 10682082 | H5: 336 | I5: 20833 | J5: =H5*I5 -> 6999888
B6: ACT002 | C6: Diseño arquitectura del sistema | D6: Arquitecto de Software | E6: 168 | F6: 40462.43 | G6: =E6*F6 -> 6797688.2 | H6: 168 | I6: 20833 | J6: =H6*I6 -> 3499944
B7: ACT003 | C7: Diseño de base de datos logística | D7: Administrador de Base de Datos | E7: 168 | F7: 28901.73 | G7: =E7*F7 -> 4855490.6 | H7: 168 | I7: 20833 | J7: =H7*I7 -> 3499944
B8: ACT004 | C8: Diseño de interfaz de usuario (UX/UI) | D8: Diseñador UX/UI | E8: 168 | F8: 26011.56 | G8: =E8*F8 -> 4369942.1 | H8: 168 | I8: 20833 | J8: =H8*I8 -> 3499944
B9: ACT005 | C9: Desarrollo módulo gestión de inventarios | D9: Desarrollador Backend Senior | E9: 336 | F9: 31791.91 | G9: =E9*F9 -> 10682082 | H9: 336 | I9: 20833 | J9: =H9*I9 -> 6999888
B10: ACT006 | C10: Desarrollo módulo gestión de pedidos | D10: Desarrollador Backend Senior | E10: 336 | F10: 31791.91 | G10: =E10*F10 -> 10682082 | H10: 336 | I10: 20833 | J10: =H10*I10 -> 6999888
B11: ACT007 | C11: Desarrollo módulo trazabilidad y despachos | D11: Desarrollador Backend Senior | E11: 168 | F11: 31791.91 | G11: =E11*F11 -> 5341040.9 | H11: 168 | I11: 20833 | J11: =H11*I11 -> 3499944
B12: ACT008 | C12: Desarrollo módulo reportes y BI básico | D12: Desarrollador Frontend | E12: 168 | F12: 28901.73 | G12: =E12*F12 -> 4855490.6 | H12: 168 | I12: 20833 | J12: =H12*I12 -> 3499944
B13: ACT009 | C13: Desarrollo de APIs e integraciones | D13: Especialista en Integración TI | E13: 252 | F13: 34682.08 | G13: =E13*F13 -> 8739884.2 | H13: 252 | I13: 20833 | J13: =H13*I13 -> 5249916
B14: ACT010 | C14: Integración con ERP existente de la empresa | D14: Especialista en Integración TI | E14: 168 | F14: 34682.08 | G14: =E14*F14 -> 5826589.4 | H14: 168 | I14: 20833 | J14: =H14*I14 -> 3499944
B15: ACT011 | C15: Pruebas funcionales y de carga | D15: Ingeniero QA / Pruebas | E15: 168 | F15: 26011.56 | G15: =E15*F15 -> 4369942.1 | H15: 168 | I15: 20833 | J15: =H15*I15 -> 3499944
B16: ACT012 | C16: Corrección de errores y ajustes | D16: Ingeniero QA / Pruebas | E16: 84 | F16: 26011.56 | G16: =E16*F16 -> 2184971 | H16: 84 | I16: 20833 | J16: =H16*I16 -> 1749972
... B22: ACT018 | C22: Evaluación final y cierre del proyecto | D22: Director de Proyecto | E22: 84 | F22: 46242.77 | G22: =E22*F22 -> 3884392.7 | H22: 84 | I22: 20833 | J22: =H22*I22 -> 1749972
B23: TOTAL COSTE ACTIVIDADES | G23: =SUM(G5:G22) -> 1.1993063e+08 | J23: =SUM(J5:J22) -> 73498824

Sheet REC_TECNICO
B1: RECURSOS TÉCNICOS – HARDWARE, SOFTWARE Y LICENCIAS
B3: A. HARDWARE
B4: Recurso | C4: Cantidad | D4: Valor Unitario (COP) | E4: Subtotal (COP)
B5: Equipos portátiles desarrollo (i7, 16GB RAM) | C5: 6 | D5: 4500000 | E5: =C5*D5 -> 27000000
B6: Servidor de pruebas local | C6: 1 | D6: 8000000 | E6: =C6*D6 -> 8000000
B7: UPS y red (switches, cableado) | C7: 1 | D7: 2500000 | E7: =C7*D7 -> 2500000
B8: Monitor adicional por desarrollador | C8: 6 | D8: 900000 | E8: =C8*D8 -> 5400000
B9: Dispositivos de almacenamiento externo | C9: 3 | D9: 400000 | E9: =C9*D9 -> 1200000
B10: SUBTOTAL HARDWARE | E10: =SUM(E5:E9) -> 44100000
B12: B. SOFTWARE Y LICENCIAS
B13: Herramienta / Servicio | C13: Unidades | D13: Valor (COP) | E13: Subtotal (COP)
B14: Licencias IDE (JetBrains – 8 meses) | C14: 6 | D14: 350000 | E14: =C14*D14 -> 2100000
B15: Hosting Cloud VPS – 8 meses (2 servidores) | C15: 2 | D15: 1200000 | E15: =C15*D15 -> 2400000
B16: Dominio web + certificado SSL (1 año) | C16: 1 | D16: 800000 | E16: =C16*D16 -> 800000
B17: Base de datos empresarial (PostgreSQL) | C17: 1 | D17: 0 | E17: =C17*D17 -> 0
B18: Sistema operativo servidores (Ubuntu Server) | C18: 2 | D18: 0 | E18: =C18*D18 -> 0
B19: Herramienta de gestión de proyectos (Jira 8m) | C19: 1 | D19: 1800000 | E19: =C19*D19 -> 1800000
B20: Repositorio código (GitHub Team 8m) | C20: 1 | D20: 600000 | E20: =C20*D20 -> 600000
B21: Licencias Office 365 (8 meses) | C21: 6 | D21: 800000 | E21: =C21*D21 -> 4800000
B22: Antivirus corporativo (8 meses) | C22: 6 | D22: 180000 | E22: =C22*D22 -> 1080000
B23: Herramienta CI/CD (GitLab CI 8m) | C23: 1 | D23: 900000 | E23: =C23*D23 -> 900000
B24: SUBTOTAL SOFTWARE Y LICENCIAS | E24: =SUM(E14:E23) -> 14480000
B25: TOTAL RECURSOS TÉCNICOS (Hardware + Software) | E25: =E10+E24 -> 58580000

Sheet IMPUESTOS
B1: IMPUESTOS Y CARGAS TRIBUTARIAS EN COLOMBIA
B3: IVA COMPRAS TECNOLÓGICAS (19%)
B4: Concepto | C4: Base Gravable (COP) | D4: IVA 19% (COP) | E4: Notas
B5: Hardware (equipos y servidores) | C5: =REC_TECNICO!E10 -> 44100000 | D5: =C5*SUPUESTOS!C11 -> 8379000 | E5: Aplica IVA 19%
B6: Software y Licencias (pagas) | C6: =REC_TECNICO!E24 -> 14480000 | D6: =C6*SUPUESTOS!C11 -> 2751200 | E6: Solo sw con costo
B7: TOTAL IVA COMPRAS TECNOLÓGICAS | D7: =SUM(D5:D6) -> 11130200
B9: NOTA: ESTAMPILLAS REGIONALES
B10: • Algunas regiones cobran estampilla departamental del 3% sobre el valor total del proyecto.
B11: • Algunas ciudades aplican estampilla municipal adicional (1%-2%).
B12: • Se debe consultar la normativa local ANTES de presentar la propuesta al cliente.
B13: • En Bogotá D.C.: Estampilla Pro-Universidad (0.5%) aplica a contratos con entidades públicas.
B14: • Si el proyecto es con entidad pública, verificar retención en la fuente (3.5%-11%).

Sheet COSTOS_OPERATIVOS
B1: COSTOS OPERATIVOS Y SERVICIOS PÚBLICOS
B3: A. SERVICIOS PÚBLICOS
B4: Servicio | C4: Valor Mensual (COP) | D4: Meses | E4: Total (COP)
B5: Energía eléctrica (oficina desarrollo) | C5: 900000 | D5: 8 | E5: =C5*D5 -> 7200000
B6: Internet empresarial fibra óptica | C6: 450000 | D6: 8 | E6: =C6*D6 -> 3600000
B7: Agua y alcantarillado | C7: 150000 | D7: 8 | E7: =C7*D7 -> 1200000
B8: Telefonía e internet móvil equipo | C8: 250000 | D8: 8 | E8: =C8*D8 -> 2000000
B9: SUBTOTAL SERVICIOS PÚBLICOS | E9: =SUM(E5:E8) -> 14000000
B11: B. OTROS COSTOS OPERATIVOS
B12: Concepto | C12: Valor (COP) | E12: Notas
B13: Papelería y suministros de oficina | C13: 1500000 | E13: 8 meses completos
B14: Transporte y viáticos del equipo | C14: 3000000 | E14: Reuniones con cliente
B15: Capacitación del equipo (nuevas tecnologías) | C15: 2500000 | E15: Cursos, talleres
B16: Seguridad informática y respaldos | C16: 2000000 | E16: Antivirus, backups
B17: Arriendo parcial espacio de trabajo | C17: 4800000 | E17: 600k/mes × 8 meses
B18: Comunicaciones y mensajería | C18: 800000 | E18: Correo, courier
B19: SUBTOTAL OTROS COSTOS OPERATIVOS | E19: =SUM(C13:C18) -> 14600000
B20: TOTAL COSTOS OPERATIVOS (SP + Otros) | E20: =E9+E19 -> 28600000

Sheet IMPREVISTOS
B1: FONDO DE IMPREVISTOS Y CONTINGENCIAS
B3: Causas de Imprevistos
B4: • Retrasos en entregas del equipo: Alta probabilidad en proyectos TI
B5: • Cambios de requerimientos del cliente: Frecuente en proyectos sin metodología ágil
B6: • Fallos técnicos de infraestructura: Servidores, red, energía
B7: • Incrementos de costos de proveedores: Inflación, TRM (si hay compras en USD)
B8: • Rotación de personal: Riesgo alto en mercado TI colombiano
B9: • Problemas de integración con ERP: Complejidad técnica elevada
B10: • Incumplimiento de SLA por terceros: Proveedores de cloud, licencias
B12: CÁLCULO DEL FONDO DE IMPREVISTOS
B13: Costo total operativo (sin imprevistos) | C13: =RESUMEN_COSTOS!C11 -> 446390200
B14: Porcentaje de imprevistos | C14: =SUPUESTOS!C10 -> 0.1
B15: TOTAL FONDO DE IMPREVISTOS (COP) | C15: =RESUMEN_COSTOS!C11*SUPUESTOS!C10 -> 44639020

Sheet RESUMEN_COSTOS
B1: RESUMEN CONSOLIDADO DE COSTOS DEL PROYECTO
B2: Proyecto: Sistema de Información Logística – 8 meses
B4: Categoría de Costo | C4: Valor (COP)
B5: 1. Mano de Obra Total (Salarios + Prestaciones 52%) | C5: =REC_HUMANO!F16+REC_HUMANO!G16 -> 348080000
B6: 2. Hardware | C6: =REC_TECNICO!E10 -> 44100000
B7: 3. Software y Licencias | C7: =REC_TECNICO!E24 -> 14480000
B8: 4. IVA Compras Tecnológicas (19%) | C8: =IMPUESTOS!D7 -> 11130200
B9: 5. Servicios Públicos | C9: =COSTOS_OPERATIVOS!E9 -> 14000000
B10: 6. Otros Costos Operativos | C10: =COSTOS_OPERATIVOS!E19 -> 14600000
B11: COSTO TOTAL OPERATIVO (sin imprevistos) | C11: =SUM(C5:C10) -> 446390200
B12: Fondo de Imprevistos (10%) | C12: =C11*SUPUESTOS!C10 -> 44639020
B13: INVERSIÓN TOTAL (Costo + Imprevistos) | C13: =C11+C12 -> 491029220
B14: Margen de Ganancia (30%) | C14: =C13*SUPUESTOS!C9 -> 147308766
B15: PRECIO FINAL DE VENTA DEL PROYECTO | C15: =C13+C14 -> 638337986

Sheet RENTABILIDAD
B1: ANÁLISIS DE RENTABILIDAD E INDICADORES FINANCIEROS
B3: RESUMEN FINANCIERO
B4: Costo total operativo | C4: =RESUMEN_COSTOS!C11 -> 446390200
B5: Fondo de imprevistos | C5: =RESUMEN_COSTOS!C12 -> 44639020
B6: Inversión total | C6: =RESUMEN_COSTOS!C13 -> 491029220
B7: Ganancia esperada (30%) | C7: =RESUMEN_COSTOS!C14 -> 147308766
B8: Valor de venta del proyecto | C8: =RESUMEN_COSTOS!C15 -> 638337986
B10: INDICADORES FINANCIEROS
B11: Indicador | C11: Resultado | D11: Interpretación
B12: Margen de utilidad sobre ventas | C12: =RESUMEN_COSTOS!C14/RESUMEN_COSTOS!C15 -> 0.23076923 | D12: Ganancia / Precio de venta
B13: Rentabilidad sobre costos (ROI) | C13: =RESUMEN_COSTOS!C14/RESUMEN_COSTOS!C13 -> 0.3 | D13: Ganancia / Inversión total
B14: Costo mensual promedio | C14: =RESUMEN_COSTOS!C13/SUPUESTOS!C5 -> 61378652 | D14: Inversión total / 8 meses
B15: Ingreso mensual promedio | C15: =RESUMEN_COSTOS!C15/SUPUESTOS!C5 -> 79792248 | D15: Precio venta / 8 meses
B16: Utilidad mensual promedio | C16: =RESUMEN_COSTOS!C14/SUPUESTOS!C5 -> 18413596 | D16: Ganancia / 8 meses
B17: Punto de equilibrio (% ejecución) | C17: =RESUMEN_COSTOS!C13/RESUMEN_COSTOS!C15 -> 0.76923077 | D17: % del proyecto que cubre costos
B18: Participación RH en costo total | C18: =(REC_HUMANO!F16+REC_HUMANO!G16)/RESUMEN_COSTOS!C11 -> 0.77976622 | D18: Recurso humano es el mayor costo
B20: FÓRMULAS GENERALES APLICADAS
B21: ▶ Costo Total = Costos Directos + Costos Indirectos + Imprevistos
B22: ▶ Precio de Venta = Costo Total + Margen de Ganancia
B23: ▶ Rentabilidad (ROI) = (Ganancia / Costos Totales) × 100
B24: ▶ Costo Hora RH = Salario Mensual / Horas Laborables Mes (173 hrs)
B25: ▶ Prestaciones = Salario Base × 52% (carga prestacional Colombia)
B26: ▶ IVA = Base Gravable × 19% (compras tecnológicas)

Sheet CLASIFICACION
B1: CLASIFICACIÓN ANALÍTICA DE COSTOS
B2: Principios de Contabilidad Analítica aplicados al proyecto
B4: COSTOS DIRECTOS | C4: COSTOS INDIRECTOS | D4: COSTOS FIJOS | E4: COSTOS VARIABLES
B5: • Salarios del equipo de desarrollo | C5: • Energía eléctrica | D5: • Salarios mensuales fijos | E5: • Transporte y reuniones
B6: • Prestaciones sociales | C6: • Internet empresarial | D6: • Internet (contrato fijo) | E6: • Viáticos por desplazamiento
B7: • Equipos de cómputo (hardware) | C7: • Administración y papelería | D7: • Hosting cloud (contrato mensual) | E7: • Soporte adicional no planificado
B8: • Licencias de herramientas de desarrollo | C8: • Transporte y viáticos | D8: • Licencias anuales / mensuales | E8: • Cambios de requerimientos
B9: • Hosting y base de datos del proyecto | C9: • Capacitación del equipo | D9: • Arriendo espacio de trabajo | E9: • Recursos adicionales por urgencias
C10: • Servicios públicos generales
B12: CENTROS DE COSTO IDENTIFICADOS
B13: Código | C13: Centro de Costo | D13: Descripción
B14: CC-001 | C14: Gestión del Proyecto | D14: Director de Proyecto – control integral
B15: CC-002 | C15: Ingeniería y Desarrollo | D15: Equipo técnico – backend, frontend, DBA
B16: CC-003 | C16: Calidad y Pruebas | D16: Ingeniero QA – validación y corrección
B17: CC-004 | C17: Infraestructura Tecnológica | D17: Servidores, cloud, redes, seguridad
B18: CC-005 | C18: Implantación y Capacitación | D18: Soporte, formación de usuarios

Sheet GANTT
B1: CRONOGRAMA DE ACTIVIDADES – DIAGRAMA DE GANTT
B2: Proyecto: Sistema de Información Logística – 8 meses
B3: No | C3: Actividad | D3: Responsable | E3: Mes 1 | F3: Mes 2 | G3: Mes 3 | H3: Mes 4 | I3: Mes 5 | J3: Mes 6 | K3: Mes 7 | L3: Mes 8
B4: ACT001 | C4: Levantamiento de requerimientos | D4: Analista Req. | E4: ■ | F4: ■
B5: ACT002 | C5: Diseño de arquitectura del sistema | D5: Arq. Software | E5: ■ | F5: ■
B6: ACT003 | C6: Diseño de base de datos | D6: DBA | F6: ■
B7: ACT004 | C7: Diseño de interfaz UX/UI | D7: Diseñador UX | F7: ■
B8: ACT005 | C8: Desarrollo módulo inventarios | D8: Dev Backend | G8: ■ | H8: ■ | I8: ■
B9: ACT006 | C9: Desarrollo módulo pedidos | D9: Dev Backend | G9: ■ | H9: ■ | I9: ■
B10: ACT007 | C10: Desarrollo módulo trazabilidad | D10: Dev Backend | H10: ■ | I10: ■
B11: ACT008 | C11: Desarrollo módulo reportes BI | D11: Dev Frontend | H11: ■ | I11: ■
B12: ACT009 | C12: Desarrollo APIs e integraciones | D12: Esp. Integr. | G12: ■ | H12: ■ | I12: ■
B13: ACT010 | C13: Integración con ERP existente | D13: Esp. Integr. | I13: ■ | J13: ■
B14: ACT011 | C14: Pruebas funcionales y de carga | D14: Ing. QA | J14: ■ | K14: ■
B15: ACT012 | C15: Corrección de errores | D15: Ing. QA | K15: ■
B16: ACT013 | C16: Config. servidores e infraestructura | D16: Arq. Software | I16: ■ | J16: ■
B17: ACT014 | C17: Implantación en producción | D17: Soporte | K17: ■ | L17: ■
B18: ACT015 | C18: Capacitación usuarios finales | D18: Dir. Proyecto | L18: ■
B19: ACT016 | C19: Documentación técnica | D19: Analista Req. | K19: ■ | L19: ■
B20: ACT017 | C20: Gestión y control del proyecto | D20: Dir. Proyecto | E20: ■ | F20: ■ | G20: ■ | H20: ■ | I20: ■ | J20: ■ | K20: ■ | L20: ■
B21: ACT018 | C21: Evaluación final y cierre | D21: Dir. Proyecto | L21: ■

Sheet RESUMEN_EJECUTIVO
B1: RESUMEN EJECUTIVO – DASHBOARD DEL PROYECTO
B2: Sistema de Información para Gestión Logística – Empresa de Distribución de Electrónicos
B4: INDICADORES CLAVE (KPIs)
B5: 💰 Inversión Total del Proyecto | C5: =RESUMEN_COSTOS!C13 -> 491029220
B6: 💵 Precio Final de Venta | C6: =RESUMEN_COSTOS!C15 -> 638337986
B7: 📈 Ganancia Esperada (30%) | C7: =RESUMEN_COSTOS!C14 -> 147308766
B8: 📅 Duración del Proyecto | C8: =SUPUESTOS!C5&" meses" -> 8 meses
B9: 👥 Total Personas en el Equipo | C9: =SUM(REC_HUMANO!C5:C14) -> 11
B10: ⚠️ Fondo de Imprevistos | C10: =RESUMEN_COSTOS!C12 -> 44639020
B11: 📊 Margen de Utilidad sobre Ventas | C11: =RESUMEN_COSTOS!C14/RESUMEN_COSTOS!C15 -> 0.23076923
B12: 🏦 ROI (Retorno sobre Inversión) | C12: =RESUMEN_COSTOS!C14/RESUMEN_COSTOS!C13 -> 0.3
B14: CONCLUSIONES DEL ANÁLISIS
B15: 1. El proyecto requiere una inversión total (con imprevistos) que cubre todos los riesgos identificados.
B16: 2. El recurso humano representa más del 70% del costo total – es el mayor factor de costo en TI.
B17: 3. La carga prestacional del 52% en Colombia es un factor crítico que no puede omitirse en el presupuesto.
B18: 4. El IVA del 19% sobre compras tecnológicas (hardware y software) incrementa significativamente el costo.
B19: 5. El fondo de imprevistos del 10% protege el proyecto ante cambios de requerimientos y retrasos.
B20: 6. Con un margen del 30%, el proyecto es financieramente viable y competitivo en el mercado colombiano.
B21: 7. La metodología ágil (Scrum/Kanban) reduciría costos de corrección y cambios de requerimientos.
B22: 8. Se recomienda monitorear mensualmente los indicadores financieros para detectar desviaciones.
B24: RECOMENDACIONES ESTRATÉGICAS
B25: ✅ Implementar control de tiempos con herramienta como Jira o ClickUp desde el día 1.
B26: ✅ Usar metodología Scrum (sprints de 2 semanas) para reducir riesgo de cambios tardíos.
... B33: Presentado por: Alejandro De Mendoza | Asignatura: Integración de Sistemas | Mayo 2026
